zarpy/__init__.py
zarpy/zarpy.so
zarpy-1.0.1.dist-info/LICENSE
zarpy-1.0.1.dist-info/METADATA
zarpy-1.0.1.dist-info/WHEEL
zarpy-1.0.1.dist-info/top_level.txt
zarpy-1.0.1.dist-info/RECORD
