Metadata-Version: 2.1
Name: zarpy
Version: 1.0.1
Summary: Formally verified biased coin and n-sided die
Author: Alexander Bagnall
Author-email: Alexander Bagnall <abagnalla@gmail.com>
License: MIT License
Project-URL: Homepage, https://github.com/bagnalla/zar
Keywords: zar,zarpy,random,sampler,biased,coin,bernoulli,uniform,die,verified,coq
Classifier: License :: OSI Approved :: MIT License
Classifier: Programming Language :: Python
Classifier: Programming Language :: Python :: 3
Requires-Python: >=3.6.3
License-File: LICENSE
